{"description":"Check TMS EXECUTOR signup page","passed":true,"pending":false,"os":"Windows NT","sessionId":"17329f05741bfbc962e389b36a086d7f","instanceId":24884,"browser":{"name":"chrome","version":"72.0.3626.81"},"message":"Passed","browserLogs":[{"level":"WARNING","message":"http://54.236.35.240/admin/register?type=EX - This page includes a password or credit card input in a non-secure context. A warning has been added to the URL bar. For more information, see https://goo.gl/zmWq3m.","timestamp":1548932695991,"type":""},{"level":"SEVERE","message":"http://54.236.35.240/favicon.png - Failed to load resource: the server responded with a status of 404 (Not Found)","timestamp":1548932697750,"type":""}],"screenShotFile":"00dd00cc-00c2-0087-00c8-00a200ef00db.png","timestamp":1548932684428,"duration":46081}
