{"description":"Check TMS EXECUTOR signup page","passed":true,"pending":false,"os":"Windows NT","sessionId":"2a9f7c7d19ad928c81c9ea2b79beb4f4","instanceId":1480,"browser":{"name":"chrome","version":"72.0.3626.81"},"message":"Passed","browserLogs":[{"level":"WARNING","message":"http://54.236.35.240/admin/register?type=EX - This page includes a password or credit card input in a non-secure context. A warning has been added to the URL bar. For more information, see https://goo.gl/zmWq3m.","timestamp":1548932177017,"type":""},{"level":"SEVERE","message":"http://54.236.35.240/favicon.png - Failed to load resource: the server responded with a status of 404 (Not Found)","timestamp":1548932178140,"type":""}],"screenShotFile":"00fa0099-0097-0063-008f-00fe00df00dd.png","timestamp":1548932164581,"duration":36844}
